lycanthropy/__init__.py
lycanthropy/_version.py
lycanthropy/lycanthropy.py
lycanthropy-1.1.0.dist-info/METADATA
lycanthropy-1.1.0.dist-info/RECORD
lycanthropy-1.1.0.dist-info/WHEEL
lycanthropy-1.1.0.dist-info/top_level.txt
