Metadata-Version: 2.1
Name: lycanthropy
Version: 1.1.0
Summary: UNKNOWN
Home-page: https://github.com/rojopolis/lycanthropy
Author: Robert Jordan
Author-email: rojopolis@deba.cl
License: UNKNOWN
Platform: UNKNOWN
